{
  "timeline": [
    "1月21日",
    "1月22日",
    "1月23日",
    "1月24日",
    "1月25日",
    "1月26日",
    "1月27日",
    "1月28日",
    "1月29日",
    "1月30日",
    "1月31日",
    "2月1日",
    "2月2日",
    "2月3日",
    "2月4日",
    "2月5日",
    "2月6日",
    "2月7日",
    "2月8日",
    "2月9日",
    "2月10日",
    "2月11日",
    "2月12日",
    "2月13日",
    "2月14日",
    "2月15日",
    "2月16日",
    "2月17日",
    "2月18日",
    "2月19日",
    "2月20日",
    "2月21日",
    "2月22日",
    "2月23日",
    "2月24日"
  ],
  "data": [
    [
      {
        "name": "郑州市",
        "value": "1"
      }
    ],
    [
      {
        "name": "郑州市",
        "value": "3"
      },
      {
        "name": "洛阳市",
        "value": "1"
      },
      {
        "name": "三门峡市",
        "value": "1"
      }
    ],
    [
      {
        "name": "郑州市",
        "value": "5"
      },
      {
        "name": "洛阳市",
        "value": "1"
      },
      {
        "name": "三门峡市",
        "value": "1"
      },
      {
        "name": "信阳市",
        "value": "1"
      },
      {
        "name": "周口市",
        "value": "1"
      }
    ],
    [
      {
        "name": "郑州市",
        "value": "8"
      },
      {
        "name": "南阳市",
        "value": "8"
      },
      {
        "name": "信阳市",
        "value": "6"
      },
      {
        "name": "周口市",
        "value": "4"
      },
      {
        "name": "驻马店市",
        "value": "2"
      },
      {
        "name": "洛阳市",
        "value": "1"
      },
      {
        "name": "三门峡市",
        "value": "1"
      },
      {
        "name": "平顶山市",
        "value": "1"
      },
      {
        "name": "新乡市",
        "value": "1"
      }
    ],
    [
      {
        "name": "信阳市",
        "value": "22"
      },
      {
        "name": "郑州市",
        "value": "20"
      },
      {
        "name": "南阳市",
        "value": "15"
      },
      {
        "name": "驻马店市",
        "value": "7"
      },
      {
        "name": "周口市",
        "value": "5"
      },
      {
        "name": "新乡市",
        "value": "3"
      },
      {
        "name": "安阳市",
        "value": "3"
      },
      {
        "name": "漯河市",
        "value": "3"
      },
      {
        "name": "三门峡市",
        "value": "2"
      },
      {
        "name": "平顶山市",
        "value": "2"
      },
      {
        "name": "洛阳市",
        "value": "1"
      }
    ],
    [
      {
        "name": "郑州市",
        "value": "29"
      },
      {
        "name": "信阳市",
        "value": "23"
      },
      {
        "name": "南阳市",
        "value": "19"
      },
      {
        "name": "周口市",
        "value": "11"
      },
      {
        "name": "驻马店市",
        "value": "9"
      },
      {
        "name": "安阳市",
        "value": "7"
      },
      {
        "name": "漯河市",
        "value": "6"
      },
      {
        "name": "商丘市",
        "value": "6"
      },
      {
        "name": "平顶山市",
        "value": "5"
      },
      {
        "name": "新乡市",
        "value": "4"
      },
      {
        "name": "三门峡市",
        "value": "3"
      },
      {
        "name": "洛阳市",
        "value": "2"
      },
      {
        "name": "鹤壁市",
        "value": "2"
      },
      {
        "name": "许昌市",
        "value": "1"
      },
      {
        "name": "开封市",
        "value": "1"
      }
    ],
    [
      {
        "name": "郑州市",
        "value": "37"
      },
      {
        "name": "信阳市",
        "value": "29"
      },
      {
        "name": "南阳市",
        "value": "26"
      },
      {
        "name": "周口市",
        "value": "15"
      },
      {
        "name": "安阳市",
        "value": "11"
      },
      {
        "name": "驻马店市",
        "value": "10"
      },
      {
        "name": "漯河市",
        "value": "9"
      },
      {
        "name": "商丘市",
        "value": "7"
      },
      {
        "name": "新乡市",
        "value": "6"
      },
      {
        "name": "平顶山市",
        "value": "5"
      },
      {
        "name": "三门峡市",
        "value": "3"
      },
      {
        "name": "洛阳市",
        "value": "2"
      },
      {
        "name": "鹤壁市",
        "value": "2"
      },
      {
        "name": "许昌市",
        "value": "2"
      },
      {
        "name": "开封市",
        "value": "2"
      },
      {
        "name": "焦作市",
        "value": "2"
      }
    ],
    [
      {
        "name": "郑州市",
        "value": "40"
      },
      {
        "name": "信阳市",
        "value": "32"
      },
      {
        "name": "南阳市",
        "value": "31"
      },
      {
        "name": "周口市",
        "value": "19"
      },
      {
        "name": "驻马店市",
        "value": "16"
      },
      {
        "name": "安阳市",
        "value": "14"
      },
      {
        "name": "商丘市",
        "value": "14"
      },
      {
        "name": "漯河市",
        "value": "9"
      },
      {
        "name": "新乡市",
        "value": "7"
      },
      {
        "name": "平顶山市",
        "value": "5"
      },
      {
        "name": "鹤壁市",
        "value": "5"
      },
      {
        "name": "三门峡市",
        "value": "4"
      },
      {
        "name": "开封市",
        "value": "3"
      },
      {
        "name": "洛阳市",
        "value": "2"
      },
      {
        "name": "许昌市",
        "value": "2"
      },
      {
        "name": "焦作市",
        "value": "2"
      },
      {
        "name": "濮阳市",
        "value": "1"
      }
    ],
    [
      {
        "name": "南阳市",
        "value": "51"
      },
      {
        "name": "郑州市",
        "value": "46"
      },
      {
        "name": "信阳市",
        "value": "42"
      },
      {
        "name": "周口市",
        "value": "25"
      },
      {
        "name": "驻马店市",
        "value": "25"
      },
      {
        "name": "商丘市",
        "value": "18"
      },
      {
        "name": "安阳市",
        "value": "17"
      },
      {
        "name": "新乡市",
        "value": "12"
      },
      {
        "name": "漯河市",
        "value": "11"
      },
      {
        "name": "平顶山市",
        "value": "8"
      },
      {
        "name": "鹤壁市",
        "value": "6"
      },
      {
        "name": "三门峡市",
        "value": "5"
      },
      {
        "name": "开封市",
        "value": "4"
      },
      {
        "name": "许昌市",
        "value": "3"
      },
      {
        "name": "洛阳市",
        "value": "2"
      },
      {
        "name": "焦作市",
        "value": "2"
      },
      {
        "name": "濮阳市",
        "value": "1"
      }
    ],
    [
      {
        "name": "南阳市",
        "value": "61"
      },
      {
        "name": "郑州市",
        "value": "50"
      },
      {
        "name": "信阳市",
        "value": "49"
      },
      {
        "name": "周口市",
        "value": "36"
      },
      {
        "name": "商丘市",
        "value": "31"
      },
      {
        "name": "驻马店市",
        "value": "30"
      },
      {
        "name": "安阳市",
        "value": "21"
      },
      {
        "name": "新乡市",
        "value": "17"
      },
      {
        "name": "漯河市",
        "value": "13"
      },
      {
        "name": "平顶山市",
        "value": "10"
      },
      {
        "name": "许昌市",
        "value": "8"
      },
      {
        "name": "鹤壁市",
        "value": "6"
      },
      {
        "name": "三门峡市",
        "value": "6"
      },
      {
        "name": "开封市",
        "value": "6"
      },
      {
        "name": "洛阳市",
        "value": "3"
      },
      {
        "name": "濮阳市",
        "value": "3"
      },
      {
        "name": "焦作市",
        "value": "2"
      }
    ],
    [
      {
        "name": "信阳市",
        "value": "70"
      },
      {
        "name": "南阳市",
        "value": "66"
      },
      {
        "name": "郑州市",
        "value": "56"
      },
      {
        "name": "驻马店市",
        "value": "40"
      },
      {
        "name": "周口市",
        "value": "38"
      },
      {
        "name": "商丘市",
        "value": "36"
      },
      {
        "name": "安阳市",
        "value": "25"
      },
      {
        "name": "新乡市",
        "value": "23"
      },
      {
        "name": "漯河市",
        "value": "14"
      },
      {
        "name": "许昌市",
        "value": "12"
      },
      {
        "name": "平顶山市",
        "value": "11"
      },
      {
        "name": "开封市",
        "value": "8"
      },
      {
        "name": "三门峡市",
        "value": "7"
      },
      {
        "name": "鹤壁市",
        "value": "6"
      },
      {
        "name": "洛阳市",
        "value": "5"
      },
      {
        "name": "濮阳市",
        "value": "3"
      },
      {
        "name": "焦作市",
        "value": "2"
      }
    ],
    [
      {
        "name": "信阳市",
        "value": "88"
      },
      {
        "name": "南阳市",
        "value": "76"
      },
      {
        "name": "郑州市",
        "value": "65"
      },
      {
        "name": "驻马店市",
        "value": "46"
      },
      {
        "name": "商丘市",
        "value": "44"
      },
      {
        "name": "周口市",
        "value": "40"
      },
      {
        "name": "安阳市",
        "value": "25"
      },
      {
        "name": "新乡市",
        "value": "23"
      },
      {
        "name": "漯河市",
        "value": "16"
      },
      {
        "name": "平顶山市",
        "value": "14"
      },
      {
        "name": "许昌市",
        "value": "13"
      },
      {
        "name": "开封市",
        "value": "11"
      },
      {
        "name": "鹤壁市",
        "value": "8"
      },
      {
        "name": "三门峡市",
        "value": "7"
      },
      {
        "name": "洛阳市",
        "value": "7"
      },
      {
        "name": "焦作市",
        "value": "7"
      },
      {
        "name": "濮阳市",
        "value": "3"
      }
    ],
    [
      {
        "name": "信阳市",
        "value": "99"
      },
      {
        "name": "南阳市",
        "value": "84"
      },
      {
        "name": "郑州市",
        "value": "72"
      },
      {
        "name": "驻马店市",
        "value": "58"
      },
      {
        "name": "商丘市",
        "value": "50"
      },
      {
        "name": "周口市",
        "value": "47"
      },
      {
        "name": "安阳市",
        "value": "29"
      },
      {
        "name": "新乡市",
        "value": "27"
      },
      {
        "name": "漯河市",
        "value": "20"
      },
      {
        "name": "平顶山市",
        "value": "19"
      },
      {
        "name": "许昌市",
        "value": "15"
      },
      {
        "name": "开封市",
        "value": "11"
      },
      {
        "name": "鹤壁市",
        "value": "8"
      },
      {
        "name": "焦作市",
        "value": "8"
      },
      {
        "name": "三门峡市",
        "value": "7"
      },
      {
        "name": "洛阳市",
        "value": "7"
      },
      {
        "name": "濮阳市",
        "value": "3"
      },
      {
        "name": "济源市",
        "value": "2"
      }
    ],
    [
      {
        "name": "信阳市",
        "value": "112"
      },
      {
        "name": "南阳市",
        "value": "99"
      },
      {
        "name": "郑州市",
        "value": "85"
      },
      {
        "name": "驻马店市",
        "value": "72"
      },
      {
        "name": "商丘市",
        "value": "60"
      },
      {
        "name": "周口市",
        "value": "52"
      },
      {
        "name": "安阳市",
        "value": "33"
      },
      {
        "name": "新乡市",
        "value": "33"
      },
      {
        "name": "平顶山市",
        "value": "28"
      },
      {
        "name": "漯河市",
        "value": "23"
      },
      {
        "name": "许昌市",
        "value": "19"
      },
      {
        "name": "开封市",
        "value": "12"
      },
      {
        "name": "焦作市",
        "value": "12"
      },
      {
        "name": "洛阳市",
        "value": "12"
      },
      {
        "name": "鹤壁市",
        "value": "10"
      },
      {
        "name": "三门峡市",
        "value": "7"
      },
      {
        "name": "濮阳市",
        "value": "4"
      },
      {
        "name": "济源市",
        "value": "2"
      }
    ],
    [
      {
        "name": "信阳市",
        "value": "138"
      },
      {
        "name": "南阳市",
        "value": "107"
      },
      {
        "name": "郑州市",
        "value": "92"
      },
      {
        "name": "驻马店市",
        "value": "82"
      },
      {
        "name": "商丘市",
        "value": "61"
      },
      {
        "name": "周口市",
        "value": "56"
      },
      {
        "name": "新乡市",
        "value": "39"
      },
      {
        "name": "安阳市",
        "value": "35"
      },
      {
        "name": "平顶山市",
        "value": "34"
      },
      {
        "name": "漯河市",
        "value": "24"
      },
      {
        "name": "许昌市",
        "value": "24"
      },
      {
        "name": "开封市",
        "value": "17"
      },
      {
        "name": "洛阳市",
        "value": "17"
      },
      {
        "name": "焦作市",
        "value": "15"
      },
      {
        "name": "鹤壁市",
        "value": "10"
      },
      {
        "name": "三门峡市",
        "value": "7"
      },
      {
        "name": "濮阳市",
        "value": "4"
      },
      {
        "name": "济源市",
        "value": "2"
      }
    ],
    [
      {
        "name": "信阳市",
        "value": "164"
      },
      {
        "name": "南阳市",
        "value": "111"
      },
      {
        "name": "郑州市",
        "value": "102"
      },
      {
        "name": "驻马店市",
        "value": "98"
      },
      {
        "name": "商丘市",
        "value": "65"
      },
      {
        "name": "周口市",
        "value": "59"
      },
      {
        "name": "新乡市",
        "value": "41"
      },
      {
        "name": "平顶山市",
        "value": "41"
      },
      {
        "name": "安阳市",
        "value": "37"
      },
      {
        "name": "漯河市",
        "value": "26"
      },
      {
        "name": "许昌市",
        "value": "26"
      },
      {
        "name": "洛阳市",
        "value": "21"
      },
      {
        "name": "开封市",
        "value": "18"
      },
      {
        "name": "焦作市",
        "value": "17"
      },
      {
        "name": "鹤壁市",
        "value": "10"
      },
      {
        "name": "三门峡市",
        "value": "7"
      },
      {
        "name": "濮阳市",
        "value": "5"
      },
      {
        "name": "济源市",
        "value": "3"
      }
    ],
    [
      {
        "name": "信阳市",
        "value": "176"
      },
      {
        "name": "南阳市",
        "value": "118"
      },
      {
        "name": "郑州市",
        "value": "112"
      },
      {
        "name": "驻马店市",
        "value": "106"
      },
      {
        "name": "商丘市",
        "value": "72"
      },
      {
        "name": "周口市",
        "value": "60"
      },
      {
        "name": "平顶山市",
        "value": "46"
      },
      {
        "name": "新乡市",
        "value": "41"
      },
      {
        "name": "安阳市",
        "value": "40"
      },
      {
        "name": "许昌市",
        "value": "28"
      },
      {
        "name": "漯河市",
        "value": "26"
      },
      {
        "name": "洛阳市",
        "value": "24"
      },
      {
        "name": "开封市",
        "value": "20"
      },
      {
        "name": "焦作市",
        "value": "18"
      },
      {
        "name": "鹤壁市",
        "value": "11"
      },
      {
        "name": "三门峡市",
        "value": "7"
      },
      {
        "name": "濮阳市",
        "value": "5"
      },
      {
        "name": "济源市",
        "value": "4"
      }
    ],
  [
{"name":"信阳市","value":"192"},
{"name":"南阳市","value":"128"},
{"name":"郑州市","value":"120"},
{"name":"驻马店市","value":"113"},
{"name":"商丘市","value":"76"},
{"name":"周口市","value":"62"},
{"name":"平顶山市","value":"48"},
{"name":"安阳市","value":"43"},
{"name":"新乡市","value":"43"},
{"name":"许昌市","value":"30"},
{"name":"漯河市","value":"29"},
{"name":"洛阳市","value":"25"},
{"name":"开封市","value":"21"},
{"name":"焦作市","value":"20"},
{"name":"鹤壁市","value":"13"},
{"name":"濮阳市","value":"7"},
{"name":"三门峡市","value":"7"},
{"name":"济源市","value":"4"}

],
[
{"name":"信阳市","value":"205"},
{"name":"南阳市","value":"133"},
{"name":"郑州市","value":"126"},
{"name":"驻马店市","value":"116"},
{"name":"商丘市","value":"82"},
{"name":"周口市","value":"62"},
{"name":"平顶山市","value":"50"},
{"name":"安阳市","value":"44"},
{"name":"新乡市","value":"44"},
{"name":"许昌市","value":"31"},
{"name":"漯河市","value":"30"},
{"name":"洛阳市","value":"25"},
{"name":"开封市","value":"24"},
{"name":"焦作市","value":"24"},
{"name":"鹤壁市","value":"17"},
{"name":"濮阳市","value":"9"},
{"name":"三门峡市","value":"7"},
{"name":"济源市","value":"4"}

],
[
{"name":"信阳市","value":"220"},
{"name":"南阳市","value":"134"},
{"name":"郑州市","value":"130"},
{"name":"驻马店市","value":"123"},
{"name":"商丘市","value":"83"},
{"name":"周口市","value":"65"},
{"name":"平顶山市","value":"52"},
{"name":"新乡市","value":"46"},
{"name":"安阳市","value":"45"},
{"name":"许昌市","value":"31"},
{"name":"漯河市","value":"30"},
{"name":"洛阳市","value":"27"},
{"name":"焦作市","value":"25"},
{"name":"开封市","value":"24"},
{"name":"鹤壁市","value":"17"},
{"name":"濮阳市","value":"10"},
{"name":"三门峡市","value":"7"},
{"name":"济源市","value":"4"}

],
[
{"name":"信阳市","value":"228"},
{"name":"南阳市","value":"136"},
{"name":"郑州市","value":"132"},
{"name":"驻马店市","value":"126"},
{"name":"商丘市","value":"86"},
{"name":"周口市","value":"65"},
{"name":"平顶山市","value":"54"},
{"name":"新乡市","value":"48"},
{"name":"安阳市","value":"46"},
{"name":"许昌市","value":"32"},
{"name":"漯河市","value":"31"},
{"name":"洛阳市","value":"28"},
{"name":"焦作市","value":"28"},
{"name":"开封市","value":"25"},
{"name":"鹤壁市","value":"18"},
{"name":"濮阳市","value":"11"},
{"name":"三门峡市","value":"7"},
{"name":"济源市","value":"4"}
],
[
{"name":"信阳市","value":"231"},
{"name":"南阳市","value":"138"},
{"name":"郑州市","value":"137"},
{"name":"驻马店市","value":"128"},
{"name":"商丘市","value":"86"},
{"name":"周口市","value":"66"},
{"name":"平顶山市","value":"55"},
{"name":"新乡市","value":"53"},
{"name":"安阳市","value":"49"},
{"name":"许昌市","value":"34"},
{"name":"漯河市","value":"33"},
{"name":"洛阳市","value":"29"},
{"name":"焦作市","value":"28"},
{"name":"开封市","value":"25"},
{"name":"鹤壁市","value":"19"},
{"name":"濮阳市","value":"13"},
{"name":"三门峡市","value":"7"},
{"name":"济源市","value":"4"}

],
[
{"name":"信阳市","value":"240"},
{"name":"南阳市","value":"145"},
{"name":"郑州市","value":"141"},
{"name":"驻马店市","value":"134"},
{"name":"商丘市","value":"87"},
{"name":"周口市","value":"68"},
{"name":"平顶山市","value":"56"},
{"name":"新乡市","value":"54"},
{"name":"安阳市","value":"50"},
{"name":"许昌市","value":"34"},
{"name":"漯河市","value":"33"},
{"name":"洛阳市","value":"30"},
{"name":"焦作市","value":"29"},
{"name":"开封市","value":"25"},
{"name":"鹤壁市","value":"19"},
{"name":"濮阳市","value":"13"},
{"name":"三门峡市","value":"7"},
{"name":"济源市","value":"4"}

],
[
{"name":"信阳市","value":"243"},
{"name":"南阳市","value":"146"},
{"name":"郑州市","value":"142"},
{"name":"驻马店市","value":"137"},
{"name":"商丘市","value":"88"},
{"name":"周口市","value":"69"},
{"name":"平顶山市","value":"57"},
{"name":"新乡市","value":"55"},
{"name":"安阳市","value":"50"},
{"name":"许昌市","value":"37"},
{"name":"漯河市","value":"33"},
{"name":"洛阳市","value":"30"},
{"name":"焦作市","value":"29"},
{"name":"开封市","value":"25"},
{"name":"鹤壁市","value":"19"},
{"name":"濮阳市","value":"13"},
{"name":"三门峡市","value":"7"},
{"name":"济源市","value":"4"}

],
[
{"name":"信阳市","value":"252"},
{"name":"南阳市","value":"150"},
{"name":"郑州市","value":"144"},
{"name":"驻马店市","value":"138"},
{"name":"商丘市","value":"90"},
{"name":"周口市","value":"70"},
{"name":"平顶山市","value":"58"},
{"name":"新乡市","value":"55"},
{"name":"安阳市","value":"51"},
{"name":"许昌市","value":"37"},
{"name":"漯河市","value":"34"},
{"name":"洛阳市","value":"31"},
{"name":"焦作市","value":"30"},
{"name":"开封市","value":"25"},
{"name":"鹤壁市","value":"19"},
{"name":"濮阳市","value":"17"},
{"name":"三门峡市","value":"7"},
{"name":"济源市","value":"4"}

],
[
{"name":"信阳市","value":"261"},
{"name":"南阳市","value":"151"},
{"name":"郑州市","value":"148"},
{"name":"驻马店市","value":"138"},
{"name":"商丘市","value":"91"},
{"name":"周口市","value":"71"},
{"name":"平顶山市","value":"58"},
{"name":"新乡市","value":"56"},
{"name":"安阳市","value":"51"},
{"name":"许昌市","value":"38"},
{"name":"漯河市","value":"34"},
{"name":"洛阳市","value":"31"},
{"name":"焦作市","value":"30"},
{"name":"开封市","value":"26"},
{"name":"鹤壁市","value":"19"},
{"name":"濮阳市","value":"17"},
{"name":"三门峡市","value":"7"},
{"name":"济源市","value":"4"}

],
[
{"name":"信阳市","value":"262"},
{"name":"南阳市","value":"154"},
{"name":"郑州市","value":"151"},
{"name":"驻马店市","value":"138"},
{"name":"商丘市","value":"91"},
{"name":"周口市","value":"75"},
{"name":"平顶山市","value":"58"},
{"name":"新乡市","value":"57"},
{"name":"安阳市","value":"51"},
{"name":"许昌市","value":"38"},
{"name":"漯河市","value":"34"},
{"name":"焦作市","value":"32"},
{"name":"洛阳市","value":"31"},
{"name":"开封市","value":"26"},
{"name":"鹤壁市","value":"19"},
{"name":"濮阳市","value":"17"},
{"name":"三门峡市","value":"7"},
{"name":"济源市","value":"5"}

],
[
{"name":"信阳市","value":"266"},
{"name":"南阳市","value":"155"},
{"name":"郑州市","value":"154"},
{"name":"驻马店市","value":"139"},
{"name":"商丘市","value":"91"},
{"name":"周口市","value":"76"},
{"name":"平顶山市","value":"58"},
{"name":"新乡市","value":"57"},
{"name":"安阳市","value":"52"},
{"name":"许昌市","value":"38"},
{"name":"漯河市","value":"34"},
{"name":"焦作市","value":"32"},
{"name":"洛阳市","value":"31"},
{"name":"开封市","value":"26"},
{"name":"鹤壁市","value":"19"},
{"name":"濮阳市","value":"17"},
{"name":"三门峡市","value":"7"},
{"name":"济源市","value":"5"}

],
[
{"name":"信阳市","value":"268"},
{"name":"郑州市","value":"156"},
{"name":"南阳市","value":"155"},
{"name":"驻马店市","value":"139"},
{"name":"商丘市","value":"91"},
{"name":"周口市","value":"76"},
{"name":"平顶山市","value":"58"},
{"name":"新乡市","value":"57"},
{"name":"安阳市","value":"52"},
{"name":"许昌市","value":"39"},
{"name":"漯河市","value":"34"},
{"name":"焦作市","value":"32"},
{"name":"洛阳市","value":"31"},
{"name":"开封市","value":"26"},
{"name":"鹤壁市","value":"19"},
{"name":"濮阳市","value":"17"},
{"name":"三门峡市","value":"7"},
{"name":"济源市","value":"5"}

],
[
{"name":"信阳市","value":"269"},
{"name":"郑州市","value":"156"},
{"name":"南阳市","value":"155"},
{"name":"驻马店市","value":"139"},
{"name":"商丘市","value":"91"},
{"name":"周口市","value":"76"},
{"name":"平顶山市","value":"58"},
{"name":"新乡市","value":"57"},
{"name":"安阳市","value":"53"},
{"name":"许昌市","value":"39"},
{"name":"漯河市","value":"35"},
{"name":"焦作市","value":"32"},
{"name":"洛阳市","value":"31"},
{"name":"开封市","value":"26"},
{"name":"鹤壁市","value":"19"},
{"name":"濮阳市","value":"17"},
{"name":"三门峡市","value":"7"},
{"name":"济源市","value":"5"}

],
[
{"name":"信阳市","value":"270"},
{"name":"郑州市","value":"157"},
{"name":"南阳市","value":"155"},
{"name":"驻马店市","value":"139"},
{"name":"商丘市","value":"91"},
{"name":"周口市","value":"76"},
{"name":"平顶山市","value":"58"},
{"name":"新乡市","value":"57"},
{"name":"安阳市","value":"53"},
{"name":"许昌市","value":"39"},
{"name":"漯河市","value":"35"},
{"name":"焦作市","value":"32"},
{"name":"洛阳市","value":"31"},
{"name":"开封市","value":"26"},
{"name":"鹤壁市","value":"19"},
{"name":"濮阳市","value":"17"},
{"name":"三门峡市","value":"7"},
{"name":"济源市","value":"5"}

],
[
{"name":"信阳市","value":"273"},
{"name":"郑州市","value":"157"},
{"name":"南阳市","value":"155"},
{"name":"驻马店市","value":"139"},
{"name":"商丘市","value":"91"},
{"name":"周口市","value":"76"},
{"name":"平顶山市","value":"58"},
{"name":"新乡市","value":"57"},
{"name":"安阳市","value":"53"},
{"name":"许昌市","value":"39"},
{"name":"漯河市","value":"35"},
{"name":"焦作市","value":"32"},
{"name":"洛阳市","value":"31"},
{"name":"开封市","value":"26"},
{"name":"鹤壁市","value":"19"},
{"name":"濮阳市","value":"17"},
{"name":"三门峡市","value":"7"},
{"name":"济源市","value":"5"}

],
[
{"name":"信阳市","value":"274"},
{"name":"郑州市","value":"157"},
{"name":"南阳市","value":"155"},
{"name":"驻马店市","value":"139"},
{"name":"商丘市","value":"91"},
{"name":"周口市","value":"76"},
{"name":"平顶山市","value":"58"},
{"name":"新乡市","value":"57"},
{"name":"安阳市","value":"53"},
{"name":"许昌市","value":"39"},
{"name":"漯河市","value":"35"},
{"name":"焦作市","value":"32"},
{"name":"洛阳市","value":"31"},
{"name":"开封市","value":"26"},
{"name":"鹤壁市","value":"19"},
{"name":"濮阳市","value":"17"},
{"name":"三门峡市","value":"7"},
{"name":"济源市","value":"5"}

],
[
{"name":"信阳市","value":"274"},
{"name":"郑州市","value":"157"},
{"name":"南阳市","value":"155"},
{"name":"驻马店市","value":"139"},
{"name":"商丘市","value":"91"},
{"name":"周口市","value":"76"},
{"name":"平顶山市","value":"58"},
{"name":"新乡市","value":"57"},
{"name":"安阳市","value":"53"},
{"name":"许昌市","value":"39"},
{"name":"漯河市","value":"35"},
{"name":"焦作市","value":"32"},
{"name":"洛阳市","value":"31"},
{"name":"开封市","value":"26"},
{"name":"鹤壁市","value":"19"},
{"name":"濮阳市","value":"17"},
{"name":"三门峡市","value":"7"},
{"name":"济源市","value":"5"}

],
[
{"name":"信阳市","value":"274"},
{"name":"郑州市","value":"157"},
{"name":"南阳市","value":"155"},
{"name":"驻马店市","value":"139"},
{"name":"商丘市","value":"91"},
{"name":"周口市","value":"76"},
{"name":"平顶山市","value":"58"},
{"name":"新乡市","value":"57"},
{"name":"安阳市","value":"53"},
{"name":"许昌市","value":"39"},
{"name":"漯河市","value":"35"},
{"name":"焦作市","value":"32"},
{"name":"洛阳市","value":"31"},
{"name":"开封市","value":"26"},
{"name":"鹤壁市","value":"19"},
{"name":"濮阳市","value":"17"},
{"name":"三门峡市","value":"7"},
{"name":"济源市","value":"5"}

]
  ],
  "title_data":{
	"Dates" : ["1月21日","1月22日","1月23日","1月24日","1月25日","1月26日","1月27日","1月28日","1月29日","1月30日","1月31日","2月1日","2月2日","2月3日","2月4日","2月5日","2月6日","2月7日","2月8日",
	"2月9日","2月10日","2月11日","2月12日","2月13日","2月14日","2月15日","2月16日","2月17日","2月18日","2月19日","2月20日","2月21日","2月22日","2月23日","2月24日"],
	"Categories" : ["1-21","1-22","1-23","1-24","1-25","1-26","1-27","1-28","1-29","1-30","1-31","2-1","2-2","2-3","2-4","2-5","2-6","2-7","2-8",
	"2-9","2-10","2-11","2-12","2-13","2-14","2-15","2-16","2-17","2-18","2-19","2-20","2-21","2-22","2-23","2-24"],
	"total" : [1,5,9,32,83,128,168,206,278,352,422,493,566,675,764,851,914,981,1033,
	1073,1105,1135,1169,1184,1212,1231,1246,1257,1262,1265,1267,1270,1271,1271,1271],
	"Cure" : [0,0,0,0,0,0,0,1,2,3,3,4,14,20,41,54,68,97,131,
	169,198,231,258,313,356,397,438,505,552,614,717,802,869,930,989],
	"Death" : [0,0,0,0,1,1,1,2,2,2,2,2,2,2,2,2,3,4,6,
	6,7,8,10,11,13,13,16,19,19,19,19,19,19,19,19],
	"ZZ" : [0,0,3,5,13,17,30,32,37,37,36,32,30,39,38,38,48,58,64,
	63,60,60,58,49,38,36,35,29,31,30,24,21,17,13,17],
	"WZZ" : [0,0,0,0,0,0,0,2,4,5,5,12,14,15,19,24,27,28,26,
	31,31,33,34,34,38,36,33,26,23,23,21,23,21,17,14],
	"QWandPT" : [1,5,6,27,69,110,137,169,233,305,376,443,506,599,664,733,768,794,806,
	804,809,803,809,777,767,749,724,678,637,579,486,405,345,292,232]
},
"policy":[[
{"name":"1月21日","value":"1"},
{"name":"1月22日","value":"0"},
{"name":"1月23日","value":"0"},
{"name":"1月24日","value":"0"},
{"name":"1月25日","value":"0"},
{"name":"1月26日","value":"0"},
{"name":"1月27日","value":"0"},
{"name":"1月28日","value":"0"},
{"name":"1月29日","value":"0"},
{"name":"1月30日","value":"0"},
{"name":"1月31日","value":"0"},
{"name":"2月1日","value":"0"},
{"name":"2月2日","value":"0"},
{"name":"2月3日","value":"0"},
{"name":"2月4日","value":"0"}
],[
{"name":"1月21日","value":"0"},
{"name":"1月22日","value":"1"},
{"name":"1月23日","value":"0"},
{"name":"1月24日","value":"0"},
{"name":"1月25日","value":"0"},
{"name":"1月26日","value":"0"},
{"name":"1月27日","value":"0"},
{"name":"1月28日","value":"0"},
{"name":"1月29日","value":"0"},
{"name":"1月30日","value":"0"},
{"name":"1月31日","value":"0"},
{"name":"2月1日","value":"0"},
{"name":"2月2日","value":"0"},
{"name":"2月3日","value":"0"},
{"name":"2月4日","value":"0"}
],[
{"name":"1月21日","value":"0"},
{"name":"1月22日","value":"0"},
{"name":"1月23日","value":"1"},
{"name":"1月24日","value":"0"},
{"name":"1月25日","value":"0"},
{"name":"1月26日","value":"0"},
{"name":"1月27日","value":"0"},
{"name":"1月28日","value":"0"},
{"name":"1月29日","value":"0"},
{"name":"1月30日","value":"0"},
{"name":"1月31日","value":"0"},
{"name":"2月1日","value":"0"},
{"name":"2月2日","value":"0"},
{"name":"2月3日","value":"0"},
{"name":"2月4日","value":"0"}
],[
{"name":"1月21日","value":"0"},
{"name":"1月22日","value":"0"},
{"name":"1月23日","value":"0"},
{"name":"1月24日","value":"1"},
{"name":"1月25日","value":"0"},
{"name":"1月26日","value":"0"},
{"name":"1月27日","value":"0"},
{"name":"1月28日","value":"0"},
{"name":"1月29日","value":"0"},
{"name":"1月30日","value":"0"},
{"name":"1月31日","value":"0"},
{"name":"2月1日","value":"0"},
{"name":"2月2日","value":"0"},
{"name":"2月3日","value":"0"},
{"name":"2月4日","value":"0"}
],[
{"name":"1月21日","value":"0"},
{"name":"1月22日","value":"0"},
{"name":"1月23日","value":"0"},
{"name":"1月24日","value":"0"},
{"name":"1月25日","value":"1"},
{"name":"1月26日","value":"0"},
{"name":"1月27日","value":"0"},
{"name":"1月28日","value":"0"},
{"name":"1月29日","value":"0"},
{"name":"1月30日","value":"0"},
{"name":"1月31日","value":"0"},
{"name":"2月1日","value":"0"},
{"name":"2月2日","value":"0"},
{"name":"2月3日","value":"0"},
{"name":"2月4日","value":"0"}
]

],
"aaa":["尹弘主持召开省政府常务会议，研究部署新型冠状病毒感染的肺炎疫情防控等工作",
"河南确认首例输入性新型冠状病毒感染的肺炎确诊病例","河南公布525家设置发热门诊医疗机构名单","河南发布关于暂停举办大型公众聚集性活动的通知","河南省正式启动重大突发公共卫生事件一级响应机制","省人民政府发布关于加强新型冠状病毒感染的肺炎疫情防控工作的通告","河南省部分城市客运班车、公交线路停运","河南将建防控应急远程会商系统，部署到130家定点医院隔离病区","河南省教育厅：疫情期间严禁补课、上课、师生聚集等活动","河南新增17所医疗定点救治医院 全省定点医院增至147所","河南企业复工日期推迟至2月9日以后","","中共河南省委办公厅、河南省人民政府办公厅印发机关学校企事业单位加强新型冠状病毒感染肺炎疫情防控工作指南","河南省各级财政全力保障疫情防控工作，加大投入力度 建立采购“绿色通道”","河南省实施疫情防控应急运输通行证制度,对应对疫情运输车辆发放AB证"
]		
}